b_delete_cf_stacks/__init__.py
b_delete_cf_stacks/delete_stacks.py
b_delete_cf_stacks/get_all_stacks.py
b_delete_cf_stacks/stack.py
b_delete_cf_stacks/commands/__init__.py
b_delete_cf_stacks/commands/delcfall.py
b_delete_cf_stacks-1.0.0.dist-info/METADATA
b_delete_cf_stacks-1.0.0.dist-info/WHEEL
b_delete_cf_stacks-1.0.0.dist-info/top_level.txt
b_delete_cf_stacks-1.0.0.dist-info/RECORD
