Metadata-Version: 2.1
Name: b-delete-cf-stacks
Version: 1.0.0
Summary: Script library to brutally delete CloudFormation stacks.
Home-page: UNKNOWN
Author: Laimonas Sutkus
Author-email: laimonas.sutkus@biomapas.com
License: Apache License 2.0
Keywords: AWS CloudFormation Boto Delete Cf
Platform: UNKNOWN
Classifier: Programming Language :: Python :: 3.8
Classifier: Operating System :: OS Independent
Requires-Dist: boto3 (<1.16.0,>=1.10.46)
